{"cameraMode":{"drawMode":0,"name":"Shaded","section":"Shading Mode"},"sceneLighting":false,"audioPlay":false,"sceneViewState":{"m_AlwaysRefresh":false,"showFog":true,"showSkybox":false,"showFlares":true,"showImageEffects":true,"showParticleSystems":true,"showVisualEffectGraphs":true,"m_FxEnabled":true},"in2DMode":false,"pivot":{"x":-0.9718169569969177,"y":16.01350212097168,"z":34.623905181884769},"rotation":{"x":-0.4963299334049225,"y":-0.5032480955123901,"z":0.48255762457847597,"w":-0.5174329280853272},"size":16.328580856323243,"orthographic":false}